pytest_powerpack/__init__.py
pytest_powerpack/comparison.py
pytest_powerpack/utils.py
pytest_powerpack-0.1.5.dist-info/LICENSE
pytest_powerpack-0.1.5.dist-info/METADATA
pytest_powerpack-0.1.5.dist-info/WHEEL
pytest_powerpack-0.1.5.dist-info/RECORD
