Metadata-Version: 2.1
Name: pytest-powerpack
Version: 0.1.5
Summary: A plugin containing extra batteries for pytest
Author: mm21
Author-email: mm21.dev@gmail.com
Requires-Python: >=3.10,<4.0
Classifier: Programming Language :: Python :: 3
Classifier: Programming Language :: Python :: 3.10
Classifier: Programming Language :: Python :: 3.11
Classifier: Programming Language :: Python :: 3.12
Requires-Dist: pyrollup (>=0.1.0,<0.2.0)
Requires-Dist: pytest (>=8.1.1,<9.0.0)
